{
	"version": "7",
	"dialect": "sqlite",
	"entries": [
		{
			"idx": 0,
			"version": "6",
			"when": 1770720659300,
			"tag": "0000_tearful_ravenous",
			"breakpoints": true
		},
		{
			"idx": 1,
			"version": "6",
			"when": 1770753003829,
			"tag": "0001_pale_deathstrike",
			"breakpoints": true
		},
		{
			"idx": 2,
			"version": "6",
			"when": 1771116207172,
			"tag": "0002_nasty_gateway",
			"breakpoints": true
		},
		{
			"idx": 3,
			"version": "6",
			"when": 1771242460450,
			"tag": "0003_freezing_gamora",
			"breakpoints": true
		},
		{
			"idx": 4,
			"version": "6",
			"when": 1772150400000,
			"tag": "0004_fix_daily_activity_pk",
			"breakpoints": true
		},
		{
			"idx": 5,
			"version": "6",
			"when": 1773542441194,
			"tag": "0005_nice_loners",
			"breakpoints": true
		},
		{
			"idx": 6,
			"version": "6",
			"when": 1773724898346,
			"tag": "0006_wooden_betty_ross",
			"breakpoints": true
		}
	]
}
